crnverifier/__init__.py
crnverifier/crn_bisimulation.py
crnverifier/crn_parser.py
crnverifier/deprecated.py
crnverifier/generate_crn.py
crnverifier/hybrid_notions.py
crnverifier/pathway_decomposition.py
crnverifier/utils.py
crnverifier/verifier.py
crnverifier-0.3.dist-info/LICENSE
crnverifier-0.3.dist-info/METADATA
crnverifier-0.3.dist-info/WHEEL
crnverifier-0.3.dist-info/entry_points.txt
crnverifier-0.3.dist-info/top_level.txt
crnverifier-0.3.dist-info/RECORD
