Metadata-Version: 2.1
Name: crnverifier
Version: 0.3
Summary: Verify the equivalence of chemical reaction networks (CRNs), or the correctness of an implementation CRN with respect to a formal CRN.
Home-page: http://www.github.com/DNA-and-Natural-Algorithms-Group/crnverifier/
Author: Stefan Badelt, Seung Woo Shin, Robert Johnson, Qing Dong, Erik Winfree
Maintainer: Stefan Badelt
Maintainer-email: bad-ants-fleet@posteo.eu
License: MIT
Platform: UNKNOWN
Classifier: Development Status :: 4 - Beta
Classifier: Programming Language :: Python :: 3.8
Classifier: Intended Audience :: Science/Research
Requires-Python: >=3.8
Requires-Dist: pyparsing
